setup.py
pytsdl/__init__.py
pytsdl/parser.py
pytsdl/tsdl.py
pytsdl.egg-info/PKG-INFO
pytsdl.egg-info/SOURCES.txt
pytsdl.egg-info/dependency_links.txt
pytsdl.egg-info/requires.txt
pytsdl.egg-info/top_level.txt