Metadata-Version: 1.0
Name: pytsdl
Version: 0.9.1
Summary: TSDL parser implemented entirely in Python 3
Home-page: https://github.com/efficios/pytsdl
Author: Philippe Proulx
Author-email: eeppeliteloop@gmail.com
License: MIT
Keywords: tsdl ctf metadata
Platform: UNKNOWN
